Workbook

Sheet Copy Audit
A1: Urbn website: content copy audit
A2: Every piece of copy on the site, where it appears, how it's used and a rating out of 10. Fill the last column with the recommended copy or a recommendation. Rating key: 9–10 keep · 7–8 polish · 5–6 rewrite · 1–4 replace or remove.
A4: # | B4: Page | C4: Where it's used | D4: Copy | E4: How it's used | F4: Rating (/10) | G4: Why this rating | H4: Recommended copy / recommendation
A5: 1 | B5: Global | C5: Site config / tagline | D5: The digital infrastructure for housing | E5: Brand line: page titles, footer, WhatsApp/OG share card, logo alt text | F5: 9 | G5: Strong, ownable positioning. Problem: it only lives in metadata and the footer; no page body copy builds this story.
A6: 2 | B6: Global | C6: Site description (default meta) | D6: Urbn is the digital infrastructure for housing in Nigeria. Every property gets a permanent, verifiable Digital Property Identity (DPI), so you can verify homes in seconds, find verified listings, and rent or buy without blind trust. | E6: Default SEO meta description + Organization schema | F6: 7 | G6: Clear and keyword-rich but ~200 characters (Google truncates ~155). 'verify / verifiable / verified' three times.
A7: 3 | B7: Global | C7: Header – desktop CTA | D7: Download App Now | E7: Primary header button (desktop) | F7: 5 | G7: 'Now' is filler urgency; inconsistent with mobile header ('Get the App').
A8: 4 | B8: Global | C8: Header – mobile CTA | D8: Get the App | E8: Compact header button (phones) | F8: 8 | G8: Short, Title Case, clear.
A9: 5 | B9: Global | C9: Header – accessibility | D9: Skip to content | E9: Keyboard skip link | F9: 9 | G9: Standard, correct.
A10: 6 | B10: Global | C10: Main navigation | D10: About us · DPI · Verify a Property · Listings · Features · Blog · FAQ | E10: Desktop nav labels | F10: 6 | G10: Mixed casing ('About us' vs 'Verify a Property'); 'About us' vs footer 'About'. DPI is jargon to first-time visitors.
A11: 7 | B11: Global | C11: Mobile tab bar | D11: Home · Listings · Verify · Features · More | E11: Bottom tab bar on phones | F11: 9 | G11: App-like, one word each, matches the app.
A12: 8 | B12: Global | C12: Mobile menu sheet – title | D12: Explore Urbn | E12: Heading of the 'More' bottom sheet | F12: 7 | G12: Fine, slightly generic.
A13: 9 | B13: Global | C13: Mobile menu sheet – items | D13: About Urbn · For Renters · For Owners · For Agents · Careers · Contact | E13: Menu sheet links | F13: 8 | G13: Clear; labels differ from footer ('For Property Owners').
A14: 10 | B14: Global | C14: Mobile menu sheet – app promo | D14: Get the Urbn app / Verify, search and book on the go | E14: App promo card inside menu sheet | F14: 6 | G14: 'on the go' is a cliché; sentence case 'app' vs 'App' elsewhere.
A15: 11 | B15: Global | C15: Footer – brand blurb | D15: The digital infrastructure for housing. Get updates as we launch in new cities, plus early access when we do. | E15: Footer text above newsletter form | F15: 6 | G15: Brand line then jumps straight to a waitlist ask with no bridge explaining what 'infrastructure' means.
A16: 12 | B16: Global | C16: Footer – column titles | D16: Company · Product · Popular | E16: Footer column headings | F16: 7 | G16: 'Popular' is vague; 'Popular areas' is clearer.
... A228: 224 | B228: Phone mockups | C228: AI search screen | D228: 2-bedroom in Bodija under ₦800k · AI Search · 3 verified matches · no filters needed | E228: Animated phone screen | F228: 8 | G228: Clear.

Sheet Summary
A1: Summary by page
A3: Page | B3: Copy items | C3: Average rating | D3: Rewrite (5–6) | E3: Replace / remove (≤4) | F3: Recommendations filled
A4: Global | B4: =COUNTIF('Copy Audit'!$B$5:$B$228,A4) | C4: =ROUND(AVERAGEIF('Copy Audit'!$B$5:$B$228,A4,'Copy Audit'!$F$5:$F$228),1) | D4: =COUNTIFS('Copy Audit'!$B$5:$B$228,A4,'Copy Audit'!$F$5:$F$228,">=5",'Copy Audit'!$F$5:$F$228,"<=6") | E4: =COUNTIFS('Copy Audit'!$B$5:$B$228,A4,'Copy Audit'!$F$5:$F$228,"<=4") | F4: =COUNTIFS('Copy Audit'!$B$5:$B$228,A4,'Copy Audit'!$H$5:$H$228,"<>")
A5: Home | B5: =COUNTIF('Copy Audit'!$B$5:$B$228,A5) | C5: =ROUND(AVERAGEIF('Copy Audit'!$B$5:$B$228,A5,'Copy Audit'!$F$5:$F$228),1) | D5: =COUNTIFS('Copy Audit'!$B$5:$B$228,A5,'Copy Audit'!$F$5:$F$228,">=5",'Copy Audit'!$F$5:$F$228,"<=6") | E5: =COUNTIFS('Copy Audit'!$B$5:$B$228,A5,'Copy Audit'!$F$5:$F$228,"<=4") | F5: =COUNTIFS('Copy Audit'!$B$5:$B$228,A5,'Copy Audit'!$H$5:$H$228,"<>")
A6: Verify | B6: =COUNTIF('Copy Audit'!$B$5:$B$228,A6) | C6: =ROUND(AVERAGEIF('Copy Audit'!$B$5:$B$228,A6,'Copy Audit'!$F$5:$F$228),1) | D6: =COUNTIFS('Copy Audit'!$B$5:$B$228,A6,'Copy Audit'!$F$5:$F$228,">=5",'Copy Audit'!$F$5:$F$228,"<=6") | E6: =COUNTIFS('Copy Audit'!$B$5:$B$228,A6,'Copy Audit'!$F$5:$F$228,"<=4") | F6: =COUNTIFS('Copy Audit'!$B$5:$B$228,A6,'Copy Audit'!$H$5:$H$228,"<>")
A7: DPI | B7: =COUNTIF('Copy Audit'!$B$5:$B$228,A7) | C7: =ROUND(AVERAGEIF('Copy Audit'!$B$5:$B$228,A7,'Copy Audit'!$F$5:$F$228),1) | D7: =COUNTIFS('Copy Audit'!$B$5:$B$228,A7,'Copy Audit'!$F$5:$F$228,">=5",'Copy Audit'!$F$5:$F$228,"<=6") | E7: =COUNTIFS('Copy Audit'!$B$5:$B$228,A7,'Copy Audit'!$F$5:$F$228,"<=4") | F7: =COUNTIFS('Copy Audit'!$B$5:$B$228,A7,'Copy Audit'!$H$5:$H$228,"<>")
A8: Listings | B8: =COUNTIF('Copy Audit'!$B$5:$B$228,A8) | C8: =ROUND(AVERAGEIF('Copy Audit'!$B$5:$B$228,A8,'Copy Audit'!$F$5:$F$228),1) | D8: =COUNTIFS('Copy Audit'!$B$5:$B$228,A8,'Copy Audit'!$F$5:$F$228,">=5",'Copy Audit'!$F$5:$F$228,"<=6") | E8: =COUNTIFS('Copy Audit'!$B$5:$B$228,A8,'Copy Audit'!$F$5:$F$228,"<=4") | F8: =COUNTIFS('Copy Audit'!$B$5:$B$228,A8,'Copy Audit'!$H$5:$H$228,"<>")
A9: Listing detail | B9: =COUNTIF('Copy Audit'!$B$5:$B$228,A9) | C9: =ROUND(AVERAGEIF('Copy Audit'!$B$5:$B$228,A9,'Copy Audit'!$F$5:$F$228),1) | D9: =COUNTIFS('Copy Audit'!$B$5:$B$228,A9,'Copy Audit'!$F$5:$F$228,">=5",'Copy Audit'!$F$5:$F$228,"<=6") | E9: =COUNTIFS('Copy Audit'!$B$5:$B$228,A9,'Copy Audit'!$F$5:$F$228,"<=4") | F9: =COUNTIFS('Copy Audit'!$B$5:$B$228,A9,'Copy Audit'!$H$5:$H$228,"<>")
A10: Area pages | B10: =COUNTIF('Copy Audit'!$B$5:$B$228,A10) | C10: =ROUND(AVERAGEIF('Copy Audit'!$B$5:$B$228,A10,'Copy Audit'!$F$5:$F$228),1) | D10: =COUNTIFS('Copy Audit'!$B$5:$B$228,A10,'Copy Audit'!$F$5:$F$228,">=5",'Copy Audit'!$F$5:$F$228,"<=6") | E10: =COUNTIFS('Copy Audit'!$B$5:$B$228,A10,'Copy Audit'!$F$5:$F$228,"<=4") | F10: =COUNTIFS('Copy Audit'!$B$5:$B$228,A10,'Copy Audit'!$H$5:$H$228,"<>")
A11: Features | B11: =COUNTIF('Copy Audit'!$B$5:$B$228,A11) | C11: =ROUND(AVERAGEIF('Copy Audit'!$B$5:$B$228,A11,'Copy Audit'!$F$5:$F$228),1) | D11: =COUNTIFS('Copy Audit'!$B$5:$B$228,A11,'Copy Audit'!$F$5:$F$228,">=5",'Copy Audit'!$F$5:$F$228,"<=6") | E11: =COUNTIFS('Copy Audit'!$B$5:$B$228,A11,'Copy Audit'!$F$5:$F$228,"<=4") | F11: =COUNTIFS('Copy Audit'!$B$5:$B$228,A11,'Copy Audit'!$H$5:$H$228,"<>")
A12: For Renters | B12: =COUNTIF('Copy Audit'!$B$5:$B$228,A12) | C12: =ROUND(AVERAGEIF('Copy Audit'!$B$5:$B$228,A12,'Copy Audit'!$F$5:$F$228),1) | D12: =COUNTIFS('Copy Audit'!$B$5:$B$228,A12,'Copy Audit'!$F$5:$F$228,">=5",'Copy Audit'!$F$5:$F$228,"<=6") | E12: =COUNTIFS('Copy Audit'!$B$5:$B$228,A12,'Copy Audit'!$F$5:$F$228,"<=4") | F12: =COUNTIFS('Copy Audit'!$B$5:$B$228,A12,'Copy Audit'!$H$5:$H$228,"<>")
A13: For Owners | B13: =COUNTIF('Copy Audit'!$B$5:$B$228,A13) | C13: =ROUND(AVERAGEIF('Copy Audit'!$B$5:$B$228,A13,'Copy Audit'!$F$5:$F$228),1) | D13: =COUNTIFS('Copy Audit'!$B$5:$B$228,A13,'Copy Audit'!$F$5:$F$228,">=5",'Copy Audit'!$F$5:$F$228,"<=6") | E13: =COUNTIFS('Copy Audit'!$B$5:$B$228,A13,'Copy Audit'!$F$5:$F$228,"<=4") | F13: =COUNTIFS('Copy Audit'!$B$5:$B$228,A13,'Copy Audit'!$H$5:$H$228,"<>")
A14: For Agents | B14: =COUNTIF('Copy Audit'!$B$5:$B$228,A14) | C14: =ROUND(AVERAGEIF('Copy Audit'!$B$5:$B$228,A14,'Copy Audit'!$F$5:$F$228),1) | D14: =COUNTIFS('Copy Audit'!$B$5:$B$228,A14,'Copy Audit'!$F$5:$F$228,">=5",'Copy Audit'!$F$5:$F$228,"<=6") | E14: =COUNTIFS('Copy Audit'!$B$5:$B$228,A14,'Copy Audit'!$F$5:$F$228,"<=4") | F14: =COUNTIFS('Copy Audit'!$B$5:$B$228,A14,'Copy Audit'!$H$5:$H$228,"<>")
A15: Audience pages | B15: =COUNTIF('Copy Audit'!$B$5:$B$228,A15) | C15: =ROUND(AVERAGEIF('Copy Audit'!$B$5:$B$228,A15,'Copy Audit'!$F$5:$F$228),1) | D15: =COUNTIFS('Copy Audit'!$B$5:$B$228,A15,'Copy Audit'!$F$5:$F$228,">=5",'Copy Audit'!$F$5:$F$228,"<=6") | E15: =COUNTIFS('Copy Audit'!$B$5:$B$228,A15,'Copy Audit'!$F$5:$F$228,"<=4") | F15: =COUNTIFS('Copy Audit'!$B$5:$B$228,A15,'Copy Audit'!$H$5:$H$228,"<>")
... A24: Phone mockups | B24: =COUNTIF('Copy Audit'!$B$5:$B$228,A24) | C24: =ROUND(AVERAGEIF('Copy Audit'!$B$5:$B$228,A24,'Copy Audit'!$F$5:$F$228),1) | D24: =COUNTIFS('Copy Audit'!$B$5:$B$228,A24,'Copy Audit'!$F$5:$F$228,">=5",'Copy Audit'!$F$5:$F$228,"<=6") | E24: =COUNTIFS('Copy Audit'!$B$5:$B$228,A24,'Copy Audit'!$F$5:$F$228,"<=4") | F24: =COUNTIFS('Copy Audit'!$B$5:$B$228,A24,'Copy Audit'!$H$5:$H$228,"<>")
A25: All pages | B25: =SUM(B4:B24) | C25: =ROUND(AVERAGE('Copy Audit'!$F$5:$F$228),1) | D25: =SUM(D4:D24) | E25: =SUM(E4:E24) | F25: =SUM(F4:F24)
A27: Biggest issues across the site
A28: 1. Brand line 'The digital infrastructure for housing' appears only in metadata, footer and share card. The page copy sells a scam checker ('before you pay'), not infrastructure.
A29: 2. Unconfirmed claims shown as fact: 10,000+ waitlist, 50 properties in verification, '1 in 3 deals', 'Nigeria's first', reply times, Property Card turnaround.
A30: 3. Invented content: the 'LaTunde Is Missing' story and the drafted Terms/Privacy must be replaced before launch.
A31: 4. Button casing is mixed; the app tone guide says Title Case for buttons ('Search Verified Homes', 'Verify a Property').
A32: 5. One feature, three names: 'AI Search', 'AI Advisor', 'AI search assistant'. Also 'neighborhood' vs 'neighbours'.
A33: 6. 'Verified' / 'DPI' repeated heavily, often 3× in one section.
A34: 7. Contradictions: 'Growing fast' vs the value 'Earn every city'; '3 steps' then 4 cards; AI search 'free' vs a daily quota.
A35: 8. Factual slip: sample plaque reads 'Off Allen Avenue, Oyo State' (Allen Avenue is in Lagos).
A36: 9. Several hero/lede paragraphs are 40–70 words, too long for phones.

Sheet Tone rules
A1: Rules to apply when writing the recommended copy
A2: • Lead with the brand line: Urbn is the digital infrastructure for housing. Verification is the proof, not the whole pitch.
A3: • Functional and direct. No exclamation marks. Avoid marketing phrases ('growing fast', 'convert', 'safer future').
A4: • Buttons and headings: Title Case. Errors, empty states and body copy: sentence case.
A5: • Money as ₦ with k/M (₦800k, ₦1.5M). Dates as DD MMM YYYY.
A6: • Only state numbers and claims that are confirmed and can be sourced.
A7: • Use 'DPI' where precision matters; 'identity' or 'record' elsewhere. Max one 'verified' per sentence.
A8: • Phone ledes: aim for ≤ 20 words. Desktop can carry a second sentence.
A9: • Local, specific details beat abstractions (caution fee, agent fee, 'five agents, five prices').
A10: • One name per feature: pick 'AI Search' or 'AI Advisor' and use it everywhere. UK spelling (neighbour, organise).
A11: • Rating key: 9–10 keep · 7–8 polish · 5–6 rewrite · 1–4 replace or remove.
